multisearch/__init__.py
multisearch/config.py
multisearch/interface/__init__.py
multisearch/interface/component.py
multisearch/interface/input.py
multisearch/interface/tui.py
multi_search-0.4.0.dist-info/entry_points.txt
multi_search-0.4.0.dist-info/LICENSE
multi_search-0.4.0.dist-info/WHEEL
multi_search-0.4.0.dist-info/METADATA
multi_search-0.4.0.dist-info/RECORD
